{
  "portfolio": [
    {
      "cover": "/portfolio/1/thomas-pak-slifer-final-v2.jpg",
      "title": "Slifer",
      "description": "React, JSX, etc, etc",
      "url": "https://www.test.com"
    },
    {
      "cover": "/portfolio/1/thomas-pak-obelisk-final.jpg",
      "title": "Slifer",
      "description": "React, JSX, etc, etc",
      "url": "https://www.test.com"
    },
    {
      "cover": "/portfolio/1/thomas-pak-ra-11.jpg",
      "title": "Slifer",
      "description": "React, JSX, etc, etc",
      "url": "https://www.test.com"
    }
  ]
}